user_blueprint/__init__.py
user_blueprint/blueprint.py
user_blueprint/user.py
user_blueprint-0.2.0.dist-info/DESCRIPTION.rst
user_blueprint-0.2.0.dist-info/METADATA
user_blueprint-0.2.0.dist-info/RECORD
user_blueprint-0.2.0.dist-info/WHEEL
user_blueprint-0.2.0.dist-info/metadata.json
user_blueprint-0.2.0.dist-info/top_level.txt
