Metadata-Version: 2.0
Name: user-blueprint
Version: 0.2.0
Summary: Flask blueprint that provides all the user handling features that are required by a web application in a database-independent way, including user registration, login, session management, password reset functionality with JWTs, automatic password hashing with Argon2 and of course the all the required route implementations with the corresponding HTML templates (styled using BlueprintJS).
Home-page: https://github.com/volfpeter/user-blueprint
Author: Peter Volf
Author-email: do.volfp@gmail.com
License: MIT
Keywords: flask blueprint user authentication login registration session templates argon2
Platform: UNKNOWN
Classifier: Development Status :: 4 - Beta
Classifier: Environment :: Web Environment
Classifier: Framework :: Flask
Classifier: Intended Audience :: Developers
Classifier: License :: OSI Approved :: MIT License
Classifier: Natural Language :: English
Classifier: Operating System :: OS Independent
Classifier: Programming Language :: Python :: 3
Classifier: Topic :: Internet :: WWW/HTTP
Classifier: Topic :: Internet :: WWW/HTTP :: Dynamic Content
Classifier: Topic :: Software Development
Classifier: Topic :: Software Development :: Libraries :: Python Modules
Requires-Python: >=3.5
Requires-Dist: flask (>=0.12)
Requires-Dist: flask-login (>=0.4)
Requires-Dist: flask-wtf (>=0.14)
Requires-Dist: passlib (>=1.7)
Requires-Dist: pyjwt (>=1.5)
